codeoven/__init__.py
codeoven/codeoven.py
codeoven/oven_utils.c
codeoven/oven_utils.h
codeoven-0.1.3.dist-info/LICENSE.txt
codeoven-0.1.3.dist-info/METADATA
codeoven-0.1.3.dist-info/WHEEL
codeoven-0.1.3.dist-info/top_level.txt
codeoven-0.1.3.dist-info/RECORD
