Metadata-Version: 2.1
Name: codeoven
Version: 0.1.3
Summary: Effortlessly integrates C code with Python.
Home-page: https://github.com/chocolate-icecream/codeoven
Author: chocolate-icecream
Project-URL: Bug Tracker, https://github.com/chocolate-icecream/codeoven/issues
Keywords: Igor
Classifier: Programming Language :: Python :: 3
Classifier: Programming Language :: Python :: 3.6
Classifier: Programming Language :: Python :: 3.7
Classifier: Programming Language :: Python :: 3.8
Classifier: Programming Language :: Python :: 3.9
Classifier: Programming Language :: Python :: 3.10
Classifier: Programming Language :: Python :: 3 :: Only
Classifier: License :: OSI Approved :: MIT License
Classifier: Operating System :: MacOS :: MacOS X
Classifier: Development Status :: 3 - Alpha
Classifier: Intended Audience :: Science/Research
Classifier: Intended Audience :: Education
Requires-Python: >=3.6
License-File: LICENSE.txt
Requires-Dist: numpy (>=1.0)
Requires-Dist: pandas (>=1.0)
